myocr_lib/__init__.py
myocr_lib/__main__.py
myocr_lib/processor.py
ocr_my-0.1.2.dist-info/METADATA
ocr_my-0.1.2.dist-info/WHEEL
ocr_my-0.1.2.dist-info/entry_points.txt
ocr_my-0.1.2.dist-info/top_level.txt
ocr_my-0.1.2.dist-info/RECORD
