Metadata-Version: 2.4
Name: ocr_my
Version: 0.1.2
Summary: A versatile OCR and document processing command-line tool.
Author-email: MyMy <mynhk@mor.com.vn>
Classifier: Programming Language :: Python :: 3
Classifier: Topic :: Text Processing
Requires-Python: >=3.8
Requires-Dist: docling-core>=0.2.0
Requires-Dist: pypdfium2
Requires-Dist: python-docx
Requires-Dist: pandas
Requires-Dist: openpyxl
Requires-Dist: Pillow
Requires-Dist: PyYAML
Requires-Dist: numpy
Requires-Dist: pydantic
Requires-Dist: rapidocr-onnxruntime
Provides-Extra: easyocr
Requires-Dist: easyocr; extra == "easyocr"
Provides-Extra: all
Requires-Dist: myocr-tool[easyocr]; extra == "all"
